[
  {
    "word": "J",
    "explanations": [
      "n  英语字母表的第十个字母；"
    ]
  },
  {
    "word": "jab",
    "explanations": [
      "n  刺，戳，捅；猛击；",
      "v  用；"
    ]
  },
  {
    "word": "jabber",
    "explanations": [
      "v  急促而含混不清地说；"
    ]
  },
  {
    "word": "jack",
    "explanations": [
      "n  机械；纸牌；球；与电有关的；",
      "v  停止；放弃；用起重器顶起，用千斤顶托起；"
    ]
  },
  {
    "word": "jackal",
    "explanations": [
      "n  豺，胡狼；"
    ]
  },
  {
    "word": "jackaroo",
    "explanations": [
      "n  牧场雇用的新手；"
    ]
  },
  {
    "word": "jackass",
    "explanations": [
      "n  笨蛋；鸟；"
    ]
  },
  {
    "word": "jackboot",
    "explanations": [
      "n  尤指纳粹分子穿的；"
    ]
  },
  {
    "word": "jackdaw",
    "explanations": [
      "n  寒鸦；"
    ]
  },
  {
    "word": "jacket",
    "explanations": [
      "n  衣服；书；"
    ]
  },
  {
    "word": "Jack",
    "explanations": [
      "n  拟人化称呼；"
    ]
  },
  {
    "word": "jack-in-the-box",
    "explanations": [
      "n  玩偶盒；"
    ]
  },
  {
    "word": "jack-knife",
    "explanations": [
      "n  大折刀；",
      "v  弯成；"
    ]
  },
  {
    "word": "jack-of-all-trades",
    "explanations": [
      "n  万事通；博而不精的人；万事通；三脚猫；南瓜灯；"
    ]
  },
  {
    "word": "jack",
    "explanations": [
      "n  单孔插头，接头；"
    ]
  },
  {
    "word": "jackpot",
    "explanations": [
      "n  比赛中的；"
    ]
  },
  {
    "word": "jackrabbit",
    "explanations": [
      "n  杰克兔；"
    ]
  },
  {
    "word": "Jack",
    "explanations": [
      "n  突然间，一眨眼工夫；说时迟那时快；"
    ]
  },
  {
    "word": "jacks",
    "explanations": [
      "n  抛接子游戏；"
    ]
  },
  {
    "word": "Jack",
    "explanations": [
      "n  自以为是的青年男子；"
    ]
  },
  {
    "word": "Jacobean",
    "explanations": [
      "adj  英王詹姆斯一世时期的；"
    ]
  },
  {
    "word": "Jacuzzi",
    "explanations": [
      "n  杰克兹浴缸；"
    ]
  },
  {
    "word": "jade",
    "explanations": [
      "n  玉；翡翠；"
    ]
  },
  {
    "word": "jaded",
    "explanations": [
      "adj  厌倦的；腻烦的；"
    ]
  },
  {
    "word": "jagged",
    "explanations": [
      "adj  有尖突的；锯齿状的；参差不齐的；"
    ]
  },
  {
    "word": "jaguar",
    "explanations": [
      "n  美洲豹，美洲虎；"
    ]
  },
  {
    "word": "jail",
    "explanations": [
      "n  监狱；看守所；",
      "v  监禁；"
    ]
  },
  {
    "word": "jailbird",
    "explanations": [
      "n  坐过牢的人，囚犯；"
    ]
  },
  {
    "word": "jailbreak",
    "explanations": [
      "n  越狱；"
    ]
  },
  {
    "word": "jailer",
    "explanations": [
      "n  监狱看守；"
    ]
  },
  {
    "word": "jalopy",
    "explanations": [
      "n  旧汽车；"
    ]
  },
  {
    "word": "jam",
    "explanations": [
      "n  食物；路上；困境；没有空间；许而不予的好东西，可望不可及的东西；知足常乐；",
      "v  卡住；音乐；推；猛然地煞车；"
    ]
  },
  {
    "word": "Jamaica",
    "explanations": [
      "n  牙买加；"
    ]
  },
  {
    "word": "Jamaican",
    "explanations": [
      "n  牙买加人；",
      "adj  牙买加人；"
    ]
  },
  {
    "word": "jamboree",
    "explanations": [
      "n  大型集会；喧闹的聚会，狂欢活动；"
    ]
  },
  {
    "word": "jammed",
    "explanations": [
      "adj  卡住；挤满的；"
    ]
  },
  {
    "word": "jammy",
    "explanations": [
      "adj  幸运的；容易的；食物；"
    ]
  },
  {
    "word": "jam-packed",
    "explanations": [
      "adj  挤得满满的，塞得紧紧的；"
    ]
  },
  {
    "word": "jam",
    "explanations": [
      "n  果酱三明治；有果酱夹馅的糕饼；"
    ]
  },
  {
    "word": "jam",
    "explanations": [
      "n  爵士；"
    ]
  },
  {
    "word": "Jane",
    "explanations": [
      "n  无名女士，某女；"
    ]
  },
  {
    "word": "jangle",
    "explanations": [
      "v  使；烦扰；"
    ]
  },
  {
    "word": "jangling",
    "explanations": [
      "n  叮铃当啷声；"
    ]
  },
  {
    "word": "January",
    "explanations": [
      "n  一月；",
      "other  一月；"
    ]
  },
  {
    "word": "Japan",
    "explanations": [
      "n  日本；"
    ]
  },
  {
    "word": "Japanese",
    "explanations": [
      "n  日语；",
      "adj  日本的；与日本有关的；"
    ]
  },
  {
    "word": "jape",
    "explanations": [
      "n  玩笑；恶作剧；"
    ]
  },
  {
    "word": "jar",
    "explanations": [
      "n  容器；摇动；",
      "v  摇动；不愉快的；不正确的；尤指噪音等；"
    ]
  },
  {
    "word": "jarful",
    "explanations": [
      "n  一罐的容量；"
    ]
  },
  {
    "word": "jargon",
    "explanations": [
      "n  行话，行业术语；"
    ]
  },
  {
    "word": "jarring",
    "explanations": [
      "adj  不愉快的；不正确的；摇动；"
    ]
  },
  {
    "word": "jasmine",
    "explanations": [
      "n  茉莉；"
    ]
  },
  {
    "word": "jaundice",
    "explanations": [
      "n  黄疸；"
    ]
  },
  {
    "word": "jaundiced",
    "explanations": [
      "adj  因从前不愉快的经历而对世事；"
    ]
  },
  {
    "word": "jaunt",
    "explanations": [
      "n  短途；",
      "v  作短途旅行；"
    ]
  },
  {
    "word": "jaunty",
    "explanations": [
      "adj  轻松活泼的；喜气洋洋的；"
    ]
  },
  {
    "word": "Java",
    "explanations": [
      "n  语言；"
    ]
  },
  {
    "word": "javelin",
    "explanations": [
      "n  标枪；"
    ]
  },
  {
    "word": "jaw",
    "explanations": [
      "n  身体部位；危险；谈话；大吃一惊；惊讶得张口结舌；",
      "v  喋喋不休，唠唠叨叨；"
    ]
  },
  {
    "word": "jaw",
    "explanations": [
      "n  下颌骨；"
    ]
  },
  {
    "word": "jawbone",
    "explanations": [
      "v  强烈呼吁；磨嘴皮子说服；"
    ]
  },
  {
    "word": "jawbreaker",
    "explanations": [
      "n  糖果；语言；难发音的词，拗口的词；",
      "pron  难发音的词，拗口的词；"
    ]
  },
  {
    "word": "jaw-dropping",
    "explanations": [
      "adj  令人惊愕的；"
    ]
  },
  {
    "word": "Jaws",
    "explanations": [
      "n  救生钳；"
    ]
  },
  {
    "word": "jay",
    "explanations": [
      "n  松鸦；"
    ]
  },
  {
    "word": "jaywalk",
    "explanations": [
      "v  不遵守交通规则乱过马路；"
    ]
  },
  {
    "word": "jazz",
    "explanations": [
      "n  爵士乐；爵士乐曲；以及诸如此类；",
      "v  使更有趣；使更吸引人；"
    ]
  },
  {
    "word": "jazzy",
    "explanations": [
      "adj  花俏的；艳丽的；爵士乐风格的；"
    ]
  },
  {
    "word": "JCB",
    "explanations": [
      "n  挖掘装载机；"
    ]
  },
  {
    "word": "J-cloth",
    "explanations": [
      "n  家用清洁布；"
    ]
  },
  {
    "word": "jealous",
    "explanations": [
      "adj  不高兴的；小心的；"
    ]
  },
  {
    "word": "jealousy",
    "explanations": [
      "n  妒忌；嫉妒；"
    ]
  },
  {
    "word": "jeans",
    "explanations": [
      "n  牛仔裤；"
    ]
  },
  {
    "word": "Jeep",
    "explanations": [
      "n  尤指军队用的；"
    ]
  },
  {
    "word": "jeepers",
    "explanations": [
      "other  表示惊讶、诧异等；"
    ]
  },
  {
    "word": "jeer",
    "explanations": [
      "v  嘲笑，嘲弄；"
    ]
  },
  {
    "word": "jeez",
    "explanations": [
      "other  表示惊讶或强烈的感情；"
    ]
  },
  {
    "word": "Jehovah",
    "explanations": [
      "n  耶和华；耶和华见证人；"
    ]
  },
  {
    "word": "jejune",
    "explanations": [
      "adj  简单的；幼稚的，不成熟的；"
    ]
  },
  {
    "word": "Jekyll",
    "explanations": [
      "n  具有善恶双重人格的人，双重性格交替出现的人；"
    ]
  },
  {
    "word": "jell",
    "explanations": [
      "v  形成胶质，胶凝；"
    ]
  },
  {
    "word": "jellied",
    "explanations": [
      "adj  成胶冻状的，胶凝了的；"
    ]
  },
  {
    "word": "jelly",
    "explanations": [
      "n  果冻；殴打；由于害怕、紧张或生病等；"
    ]
  },
  {
    "word": "jelly",
    "explanations": [
      "n  胶糖娃娃；"
    ]
  },
  {
    "word": "jelly",
    "explanations": [
      "n  豆型软心糖；"
    ]
  },
  {
    "word": "jellyfish",
    "explanations": [
      "n  水母；海蜇；"
    ]
  },
  {
    "word": "jemmy",
    "explanations": [
      "n  窃贼等用来撬开门窗的；",
      "v  用撬棍撬；"
    ]
  },
  {
    "word": "je",
    "explanations": [
      "n  难以描绘；"
    ]
  },
  {
    "word": "jeopardize",
    "explanations": [
      "v  使处于危险境地；危及，损害；"
    ]
  },
  {
    "word": "jeopardy",
    "explanations": [
      "n  处于危险之中；"
    ]
  },
  {
    "word": "jerk",
    "explanations": [
      "n  移动；人；",
      "v  使；男人；"
    ]
  },
  {
    "word": "jerkin",
    "explanations": [
      "n  无袖；"
    ]
  },
  {
    "word": "jerkwater",
    "explanations": [
      "n  某地；",
      "adj  某地；"
    ]
  },
  {
    "word": "jerky",
    "explanations": [
      "n  条状；",
      "adj  忽动忽停的；抽动的，痉挛性的；"
    ]
  },
  {
    "word": "jeroboam",
    "explanations": [
      "n  大酒瓶；"
    ]
  },
  {
    "word": "jerry-built",
    "explanations": [
      "adj  偷工减料建成的，用劣质材料草草建成的；"
    ]
  },
  {
    "word": "jerry",
    "explanations": [
      "n  盛放液体燃料或水的；"
    ]
  },
  {
    "word": "Jersey",
    "explanations": [
      "n  泽西牛；"
    ]
  },
  {
    "word": "jersey",
    "explanations": [
      "n  衣服；布料；"
    ]
  },
  {
    "word": "Jerusalem",
    "explanations": [
      "n  菊芋，洋姜，耶路撒冷洋蓟；"
    ]
  },
  {
    "word": "jest",
    "explanations": [
      "n  笑话；滑稽事；戏言寓真理；",
      "v  开玩笑；"
    ]
  },
  {
    "word": "jester",
    "explanations": [
      "n  旧时的；"
    ]
  },
  {
    "word": "Jesuit",
    "explanations": [
      "n  耶稣会会士；"
    ]
  },
  {
    "word": "Jesus",
    "explanations": [
      "n  耶稣，耶稣基督；",
      "other  表示惊讶、震惊或恼怒；"
    ]
  },
  {
    "word": "jet",
    "explanations": [
      "n  飞机；流；石头；",
      "v  搭飞机旅行；"
    ]
  },
  {
    "word": "jet-black",
    "explanations": [
      "adj  乌黑的；"
    ]
  },
  {
    "word": "jet",
    "explanations": [
      "n  喷射引擎；"
    ]
  },
  {
    "word": "jetfoil",
    "explanations": [
      "n  飞翼船；"
    ]
  },
  {
    "word": "jet",
    "explanations": [
      "n  时差；"
    ]
  },
  {
    "word": "jetliner",
    "explanations": [
      "n  喷射客机；"
    ]
  },
  {
    "word": "jet",
    "explanations": [
      "n  喷射推进；"
    ]
  },
  {
    "word": "jetsam",
    "explanations": [
      "n  冲到岸上的；"
    ]
  },
  {
    "word": "jet-set",
    "explanations": [
      "v  很享受地；"
    ]
  },
  {
    "word": "jet-setter",
    "explanations": [
      "n  环游世界享乐的；"
    ]
  },
  {
    "word": "jet",
    "explanations": [
      "n  一至二人乘坐的；"
    ]
  },
  {
    "word": "jet",
    "explanations": [
      "n  地球高空自西向东的；"
    ]
  },
  {
    "word": "jettison",
    "explanations": [
      "v  把；"
    ]
  },
  {
    "word": "jetty",
    "explanations": [
      "n  登岸码头，突堤，栈桥；"
    ]
  },
  {
    "word": "jetway",
    "explanations": [
      "n  旅客登机桥，登机栈桥；"
    ]
  },
  {
    "word": "Jew",
    "explanations": [
      "n  犹太人；犹太教徒；"
    ]
  },
  {
    "word": "jewel",
    "explanations": [
      "n  宝石；美丽；人；王冠上的宝石，最珍贵的部分；"
    ]
  },
  {
    "word": "jewel",
    "explanations": [
      "n  装光碟的；"
    ]
  },
  {
    "word": "jewelled",
    "explanations": [
      "adj  用宝石装饰的；"
    ]
  },
  {
    "word": "jeweller",
    "explanations": [
      "n  珠宝商；钟表商；"
    ]
  },
  {
    "word": "jewelleryUK",
    "explanations": [
      "n  总称；"
    ]
  },
  {
    "word": "jewellery",
    "explanations": [
      "n  珠宝盒，首饰箱；"
    ]
  },
  {
    "word": "jewfish",
    "explanations": [
      "n  大海鲈；"
    ]
  },
  {
    "word": "Jewry",
    "explanations": [
      "n  总称；单簧口琴；"
    ]
  },
  {
    "word": "Jezebel",
    "explanations": [
      "n  无耻荡妇；"
    ]
  },
  {
    "word": "jib",
    "explanations": [
      "n  船；起重工具；",
      "v  不愿做；虽然这项税收不得人心，政府也不愿将之完全废除；"
    ]
  },
  {
    "word": "jibe",
    "explanations": [
      "n  嘲讽；",
      "v  嘲讽，嘲弄，嘲笑；与；"
    ]
  },
  {
    "word": "jiffy",
    "explanations": [
      "n  一会儿，瞬间；"
    ]
  },
  {
    "word": "Jiffy",
    "explanations": [
      "n  厚层信封；"
    ]
  },
  {
    "word": "jig",
    "explanations": [
      "n  舞蹈；工具；",
      "v  使；"
    ]
  },
  {
    "word": "jigger",
    "explanations": [
      "n  小量杯；一小量杯的酒；",
      "v  尤指不公正或非法地；"
    ]
  },
  {
    "word": "jiggered",
    "explanations": [
      "adj  筋疲力竭的；大吃一惊；"
    ]
  },
  {
    "word": "jiggery-pokery",
    "explanations": [
      "n  欺骗行为；骗局；搞鬼；"
    ]
  },
  {
    "word": "jiggle",
    "explanations": [
      "v  使；"
    ]
  },
  {
    "word": "jigsaw",
    "explanations": [
      "n  图片游戏；神秘；工具；"
    ]
  },
  {
    "word": "jihad",
    "explanations": [
      "n  伊斯兰教的；"
    ]
  },
  {
    "word": "jillaroo",
    "explanations": [
      "n  牧场见习女工；"
    ]
  },
  {
    "word": "jilt",
    "explanations": [
      "v  突然抛弃；"
    ]
  },
  {
    "word": "Jim",
    "explanations": [
      "n  美国对黑人的；"
    ]
  },
  {
    "word": "jim-dandy",
    "explanations": [
      "n  出色的东西，极好之物；"
    ]
  },
  {
    "word": "jimjams",
    "explanations": [
      "n  睡衣裤；"
    ]
  },
  {
    "word": "jingle",
    "explanations": [
      "n  曲调；响；",
      "v  使；"
    ]
  },
  {
    "word": "jingoism",
    "explanations": [
      "n  极端爱国主义；侵略主义；沙文主义；"
    ]
  },
  {
    "word": "jingoist",
    "explanations": [
      "n  沙文主义者；"
    ]
  },
  {
    "word": "jinx",
    "explanations": [
      "n  厄运；不祥的人；"
    ]
  },
  {
    "word": "jitney",
    "explanations": [
      "n  按固定路线行驶的；"
    ]
  },
  {
    "word": "jitters",
    "explanations": [
      "n  极度的；使；"
    ]
  },
  {
    "word": "jittery",
    "explanations": [
      "adj  紧张不安的；心烦意乱的；"
    ]
  },
  {
    "word": "jive",
    "explanations": [
      "n  舞蹈；讲话；",
      "v  舞蹈；讲话；"
    ]
  },
  {
    "word": "Jnr",
    "explanations": [
      "n  小；",
      "adj  小；",
      "other  小；"
    ]
  },
  {
    "word": "job",
    "explanations": [
      "n  雇用；一件工作；职责；难题；产品；东西；犯罪；正是想要的东西；做得出色；有效，起作用；工作不允许；；做得好；身居要职的人；最适合的人选；工作时发生的；在职的；",
      "v  把脚踏车的轮子拆下来可真费力；"
    ]
  },
  {
    "word": "job",
    "explanations": [
      "n  职工抗议行动；"
    ]
  },
  {
    "word": "jobbing",
    "explanations": [
      "adj  临时演员；"
    ]
  },
  {
    "word": "job",
    "explanations": [
      "n  就业服务中心；"
    ]
  },
  {
    "word": "job",
    "explanations": [
      "n  创造就业；"
    ]
  },
  {
    "word": "job",
    "explanations": [
      "n  职务描述；"
    ]
  },
  {
    "word": "job",
    "explanations": [
      "n  工作评估；职位评定；"
    ]
  },
  {
    "word": "jobless",
    "explanations": [
      "n  失业者，失业人士；",
      "adj  失业的；"
    ]
  },
  {
    "word": "job",
    "explanations": [
      "n  以较低价格买卖的；"
    ]
  },
  {
    "word": "job",
    "explanations": [
      "n  工作满足感；"
    ]
  },
  {
    "word": "job",
    "explanations": [
      "n  职业稳定性；"
    ]
  },
  {
    "word": "jobseeker",
    "explanations": [
      "n  求职者；英国；",
      "other  英国；"
    ]
  },
  {
    "word": "jobshare",
    "explanations": [
      "v  两人；"
    ]
  },
  {
    "word": "jobsworth",
    "explanations": [
      "n  墨守成规者；"
    ]
  },
  {
    "word": "Jock",
    "explanations": [
      "n  苏格兰佬；"
    ]
  },
  {
    "word": "jock",
    "explanations": [
      "n  人；内衣；"
    ]
  },
  {
    "word": "jockey",
    "explanations": [
      "n  职业赛马骑师；",
      "v  运用各种手段谋利；诱骗；多名老板最终被哄骗在工会协议上签字；"
    ]
  },
  {
    "word": "jockstrap",
    "explanations": [
      "n  男运动员用的；"
    ]
  },
  {
    "word": "jocose",
    "explanations": [
      "adj  滑稽的；幽默的；诙谐的；"
    ]
  },
  {
    "word": "jocular",
    "explanations": [
      "adj  有趣的；逗乐的；"
    ]
  },
  {
    "word": "jodhpurs",
    "explanations": [
      "n  马裤；"
    ]
  },
  {
    "word": "Joe",
    "explanations": [
      "n  普通人，平常人；"
    ]
  },
  {
    "word": "Joe",
    "explanations": [
      "n  老百姓，平民百姓，大众；"
    ]
  },
  {
    "word": "joey",
    "explanations": [
      "n  幼袋鼠；"
    ]
  },
  {
    "word": "jog",
    "explanations": [
      "n  慢跑；",
      "v  跑；推；前进；唤起；缓慢平稳地进行；"
    ]
  },
  {
    "word": "jogger",
    "explanations": [
      "n  慢跑者；"
    ]
  },
  {
    "word": "jogging",
    "explanations": [
      "n  慢跑；"
    ]
  },
  {
    "word": "jogging",
    "explanations": [
      "n  慢跑运动服；"
    ]
  },
  {
    "word": "joggle",
    "explanations": [
      "v  轻轻颠动；"
    ]
  },
  {
    "word": "jog-trot",
    "explanations": [
      "n  慢跑；"
    ]
  },
  {
    "word": "john",
    "explanations": [
      "n  厕所；人；"
    ]
  },
  {
    "word": "John",
    "explanations": [
      "n  约翰牛；"
    ]
  },
  {
    "word": "John",
    "explanations": [
      "n  无名氏，某甲；"
    ]
  },
  {
    "word": "John",
    "explanations": [
      "n  海鲂；"
    ]
  },
  {
    "word": "John",
    "explanations": [
      "n  亲笔签名；"
    ]
  },
  {
    "word": "johnny",
    "explanations": [
      "n  保险套；"
    ]
  },
  {
    "word": "johnny-come-lately",
    "explanations": [
      "n  新来者；一夜成名者；新贵；"
    ]
  },
  {
    "word": "joie",
    "explanations": [
      "n  生活之乐；人生的极大乐趣；"
    ]
  },
  {
    "word": "join",
    "explanations": [
      "n  接头；结点；接合处；",
      "v  连接；一起做；成为成员；结为夫妻；参战；携手；挽手；彼此彼此；参加；从军，入伍；"
    ]
  },
  {
    "word": "joined-up",
    "explanations": [
      "adj  连写的；草书的；"
    ]
  },
  {
    "word": "joined-up",
    "explanations": [
      "n  统筹思考；"
    ]
  },
  {
    "word": "joiner",
    "explanations": [
      "n  木匠，木工；"
    ]
  },
  {
    "word": "joinery",
    "explanations": [
      "n  细木工业；细木工的制品；"
    ]
  },
  {
    "word": "joint",
    "explanations": [
      "n  身体；连接；肉；地方；毒品；使混乱；使无秩序；",
      "v  把；",
      "adj  共有的，共用的；共同的；"
    ]
  },
  {
    "word": "jointed",
    "explanations": [
      "adj  身体；连接；"
    ]
  },
  {
    "word": "joint",
    "explanations": [
      "n  美国国会两院的；"
    ]
  },
  {
    "word": "joint-stock",
    "explanations": [
      "n  合股公司；"
    ]
  },
  {
    "word": "joist",
    "explanations": [
      "n  椼；托梁；"
    ]
  },
  {
    "word": "jojoba",
    "explanations": [
      "n  霍霍巴树，加州希蒙得木；"
    ]
  },
  {
    "word": "joke",
    "explanations": [
      "n  有趣的；坏；不是闹着玩的；不是轻而易举的事；超出开玩笑的限度，开始令人恼怒；开玩笑反而开到；对；经得起玩笑话，开得起玩笑；",
      "v  说笑话；言归正传，说正经的；只是在开玩笑；表示不相信或觉得荒谬；表示吃惊或不相信；"
    ]
  },
  {
    "word": "joker",
    "explanations": [
      "n  牌；有趣的人；讨厌的人；能意想不到地改变形势的人；"
    ]
  },
  {
    "word": "jokester",
    "explanations": [
      "n  逗乐的人；"
    ]
  },
  {
    "word": "jokey",
    "explanations": [
      "adj  有趣的，滑稽的；"
    ]
  },
  {
    "word": "jokingly",
    "explanations": [
      "v  打趣地，戏谑地；",
      "adv  打趣地，戏谑地；"
    ]
  },
  {
    "word": "jollies",
    "explanations": [
      "n  尤指从令人不愉快的事中；"
    ]
  },
  {
    "word": "jollification",
    "explanations": [
      "n  欢庆；欢宴；"
    ]
  },
  {
    "word": "jolly",
    "explanations": [
      "v  很，非常；表示赞同、已听到或明白；表示赞赏；说好话；使更明亮悦目；",
      "adj  高兴的；令人愉快的；吸引人的；上层社会女子；",
      "adv  很，非常；表示赞同、已听到或明白；表示赞赏；"
    ]
  },
  {
    "word": "jolly",
    "explanations": [
      "v  用于生气或烦心时加强语气；",
      "adv  用于生气或烦心时加强语气；"
    ]
  },
  {
    "word": "jolt",
    "explanations": [
      "n  动作；震惊；",
      "v  突然移动；震惊；"
    ]
  },
  {
    "word": "jones",
    "explanations": [
      "v  非常需要；很想要；"
    ]
  },
  {
    "word": "Jordan",
    "explanations": [
      "n  约旦；"
    ]
  },
  {
    "word": "Jordanian",
    "explanations": [
      "n  约旦人；",
      "adj  约旦人；"
    ]
  },
  {
    "word": "josh",
    "explanations": [
      "v  戏弄；对；"
    ]
  },
  {
    "word": "joss",
    "explanations": [
      "n  缓缓燃烧并发出香味的；"
    ]
  },
  {
    "word": "jostle",
    "explanations": [
      "v  挤；推；撞；为；"
    ]
  },
  {
    "word": "jot",
    "explanations": [
      "n  一点也没有，丝毫没有；",
      "v  草草记下；匆匆记下；匆匆记下，草草记下；"
    ]
  },
  {
    "word": "jotter",
    "explanations": [
      "n  笔记本，便条簿；"
    ]
  },
  {
    "word": "jottings",
    "explanations": [
      "n  匆匆记下的东西；摘记；便条；"
    ]
  },
  {
    "word": "joule",
    "explanations": [
      "n  焦耳；",
      "other  焦耳；"
    ]
  },
  {
    "word": "journal",
    "explanations": [
      "n  杂志；纪录；"
    ]
  },
  {
    "word": "journalese",
    "explanations": [
      "n  满是陈腔滥调的；"
    ]
  },
  {
    "word": "journalism",
    "explanations": [
      "n  新闻工作；新闻业；"
    ]
  },
  {
    "word": "journalist",
    "explanations": [
      "n  新闻记者；报纸撰稿人；广播员；"
    ]
  },
  {
    "word": "journey",
    "explanations": [
      "n  尤指搭乘交通工具的；",
      "v  旅行；"
    ]
  },
  {
    "word": "journeyman",
    "explanations": [
      "n  雇佣；短工；"
    ]
  },
  {
    "word": "joust",
    "explanations": [
      "v  旧时；"
    ]
  },
  {
    "word": "jovial",
    "explanations": [
      "adj  人；"
    ]
  },
  {
    "word": "jowl",
    "explanations": [
      "n  双下巴，下颌垂肉；"
    ]
  },
  {
    "word": "joy",
    "explanations": [
      "n  高兴；成功；",
      "v  你找到你想要的那本书了吗；"
    ]
  },
  {
    "word": "joyful",
    "explanations": [
      "adj  高兴的，快乐的；"
    ]
  },
  {
    "word": "joyless",
    "explanations": [
      "adj  不欢乐的，不快活的；"
    ]
  },
  {
    "word": "joyous",
    "explanations": [
      "adj  高兴的，欢快的；"
    ]
  },
  {
    "word": "joypad",
    "explanations": [
      "n  手柄；"
    ]
  },
  {
    "word": "joyriding",
    "explanations": [
      "n  驾驶偷来的汽车兜风；偷开车；"
    ]
  },
  {
    "word": "joystick",
    "explanations": [
      "n  操纵杆，驾驶杆；"
    ]
  },
  {
    "word": "JPEG",
    "explanations": [
      "n  联合图像专家组；",
      "other  联合图像专家组；"
    ]
  },
  {
    "word": "jubilant",
    "explanations": [
      "adj  尤指因成功而；"
    ]
  },
  {
    "word": "jubilation",
    "explanations": [
      "n  尤指因成功而；"
    ]
  },
  {
    "word": "jubilee",
    "explanations": [
      "n  重要事件的；"
    ]
  },
  {
    "word": "Judaeo-ChristianUK",
    "explanations": [
      "adj  犹太教；"
    ]
  },
  {
    "word": "Judaic",
    "explanations": [
      "adj  犹太教的；犹太特征的；"
    ]
  },
  {
    "word": "Judaism",
    "explanations": [
      "n  犹太教；"
    ]
  },
  {
    "word": "Judas",
    "explanations": [
      "n  出卖朋友的人，叛徒；"
    ]
  },
  {
    "word": "judder",
    "explanations": [
      "v  尤指车辆；"
    ]
  },
  {
    "word": "judge",
    "explanations": [
      "n  人；决定；",
      "v  尤指认真考虑之后；勿只凭外表判断；不能以貌取人；"
    ]
  },
  {
    "word": "judgment",
    "explanations": [
      "n  判断；法定；我们还在等待法院对此案的裁决；",
      "pron  我们还在等待法院对此案的裁决；"
    ]
  },
  {
    "word": "judgmental",
    "explanations": [
      "adj  动辄就品头论足的，动不动就批评人的；"
    ]
  },
  {
    "word": "judgment",
    "explanations": [
      "n  主观判断；"
    ]
  },
  {
    "word": "Judgment",
    "explanations": [
      "n  上帝对人类的；"
    ]
  },
  {
    "word": "judicature",
    "explanations": [
      "n  司法；"
    ]
  },
  {
    "word": "judicial",
    "explanations": [
      "adj  司法的；审判；"
    ]
  },
  {
    "word": "judiciary",
    "explanations": [
      "n  政府的；",
      "v  政府的；"
    ]
  },
  {
    "word": "judicious",
    "explanations": [
      "adj  明断的；明智而审慎的；"
    ]
  },
  {
    "word": "judo",
    "explanations": [
      "n  柔道；"
    ]
  },
  {
    "word": "jug",
    "explanations": [
      "n  容器；监狱；"
    ]
  },
  {
    "word": "juggernaut",
    "explanations": [
      "n  车辆；强大的力量；"
    ]
  },
  {
    "word": "juggle",
    "explanations": [
      "v  娱乐；应付；改变；"
    ]
  },
  {
    "word": "juggler",
    "explanations": [
      "n  玩杂耍的人；"
    ]
  },
  {
    "word": "juggling",
    "explanations": [
      "n  需同时处理几件不同事情的；"
    ]
  },
  {
    "word": "jugular",
    "explanations": [
      "n  颈静脉；攻击要害；给予致命一击；"
    ]
  },
  {
    "word": "juice",
    "explanations": [
      "n  液体；力量；能力；"
    ]
  },
  {
    "word": "juicer",
    "explanations": [
      "n  榨汁机，榨汁器；"
    ]
  },
  {
    "word": "juicy",
    "explanations": [
      "n  大的；重要的；高品质的；资讯；",
      "adj  液体；好的；"
    ]
  },
  {
    "word": "ju-jitsu",
    "explanations": [
      "n  柔术；"
    ]
  },
  {
    "word": "jukebox",
    "explanations": [
      "n  丢进硬币后播放唱片的；"
    ]
  },
  {
    "word": "July",
    "explanations": [
      "n  七月；",
      "other  七月；"
    ]
  },
  {
    "word": "jumble",
    "explanations": [
      "n  混杂；旧的东西；",
      "v  使杂乱；使混乱；"
    ]
  },
  {
    "word": "jumble",
    "explanations": [
      "n  尤指为机构筹款的；"
    ]
  },
  {
    "word": "jumbo",
    "explanations": [
      "n  特大；",
      "adj  特大；"
    ]
  },
  {
    "word": "jumbo",
    "explanations": [
      "n  巨型飞机；"
    ]
  },
  {
    "word": "jump",
    "explanations": [
      "n  动作；增加；占先；抢先；抢在；",
      "v  在空中；突然移动；增加；顺序；避免；攻击；非法移动；忙；生气，恼怒；快滚，滚开；愤怒回击；非常高兴；不加考虑就仓促参与；尤指不经仔细考虑；贸然断定；过早下结论；赶快做，积极行动；立刻为；欣然接受；打断，插嘴；责备，责骂，批评；使；"
    ]
  },
  {
    "word": "jumped-up",
    "explanations": [
      "n  尤指因地位显著提升后；",
      "adj  尤指因地位显著提升后；"
    ]
  },
  {
    "word": "jumper",
    "explanations": [
      "n  衣服；空中；"
    ]
  },
  {
    "word": "jumping-off",
    "explanations": [
      "n  起点，出发点；"
    ]
  },
  {
    "word": "jump",
    "explanations": [
      "n  用来与另一辆汽车中带电电池相连接以启动引擎的；"
    ]
  },
  {
    "word": "jump",
    "explanations": [
      "n  跳绳；",
      "v  跳绳；"
    ]
  },
  {
    "word": "jump-start",
    "explanations": [
      "v  助推起动；"
    ]
  },
  {
    "word": "jumpsuit",
    "explanations": [
      "n  连衫裤；"
    ]
  },
  {
    "word": "jumpy",
    "explanations": [
      "adj  提心吊胆的；胆战心惊的；紧张不安的；"
    ]
  },
  {
    "word": "junction",
    "explanations": [
      "n  联结点；枢纽；；"
    ]
  },
  {
    "word": "junction",
    "explanations": [
      "n  接线箱，分线盒；"
    ]
  },
  {
    "word": "juncture",
    "explanations": [
      "n  时刻；关头；"
    ]
  },
  {
    "word": "June",
    "explanations": [
      "n  六月；",
      "other  六月；"
    ]
  },
  {
    "word": "Jungian",
    "explanations": [
      "adj  荣格的；"
    ]
  },
  {
    "word": "jungle",
    "explanations": [
      "n  丛林；不整洁的地方；局面；音乐；"
    ]
  },
  {
    "word": "jungle",
    "explanations": [
      "n  丛林战；"
    ]
  },
  {
    "word": "junior",
    "explanations": [
      "n  低级别；学生；较年幼者；儿子；",
      "adj  低级别；较年幼的；",
      "other  置于姓名后表示家庭同名两人中的较年幼者；"
    ]
  },
  {
    "word": "junior",
    "explanations": [
      "n  两年制专科学校，大专；"
    ]
  },
  {
    "word": "junior",
    "explanations": [
      "n  初级中学；"
    ]
  },
  {
    "word": "junior",
    "explanations": [
      "n  英国的；"
    ]
  },
  {
    "word": "juniper",
    "explanations": [
      "n  桧属植物；杜松；刺柏；"
    ]
  },
  {
    "word": "junk",
    "explanations": [
      "n  垃圾；毒品；船；",
      "v  丢弃，扔掉；"
    ]
  },
  {
    "word": "junket",
    "explanations": [
      "n  政府官员的；"
    ]
  },
  {
    "word": "junk",
    "explanations": [
      "n  垃圾食品；"
    ]
  },
  {
    "word": "junkie",
    "explanations": [
      "n  瘾君子，有毒瘾者；"
    ]
  },
  {
    "word": "junk",
    "explanations": [
      "n  垃圾邮件；"
    ]
  },
  {
    "word": "junk",
    "explanations": [
      "n  出售旧家俱等的；"
    ]
  },
  {
    "word": "junkyard",
    "explanations": [
      "n  堆放旧家俱、旧机器等的；"
    ]
  },
  {
    "word": "junta",
    "explanations": [
      "n  以武力夺取政权的；",
      "v  以武力夺取政权的；"
    ]
  },
  {
    "word": "Jupiter",
    "explanations": [
      "n  木星；"
    ]
  },
  {
    "word": "Jurassic",
    "explanations": [
      "adj  侏罗纪的；"
    ]
  },
  {
    "word": "jurisdiction",
    "explanations": [
      "n  司法权；管辖权；审判权；"
    ]
  },
  {
    "word": "jurisprudence",
    "explanations": [
      "n  法学；法律学；"
    ]
  },
  {
    "word": "jurist",
    "explanations": [
      "n  法学家；法律专家；；"
    ]
  },
  {
    "word": "juror",
    "explanations": [
      "n  陪审员；陪审团成员；"
    ]
  },
  {
    "word": "jury",
    "explanations": [
      "n  陪审团；答案或观点；",
      "v  陪审团；答案或观点；"
    ]
  },
  {
    "word": "jury",
    "explanations": [
      "n  陪审；"
    ]
  },
  {
    "word": "jury",
    "explanations": [
      "n  陪审义务，担任陪审员期间；"
    ]
  },
  {
    "word": "jus",
    "explanations": [
      "n  汁，调味汁；"
    ]
  },
  {
    "word": "just",
    "explanations": [
      "n  公正的人，有正义感的人；",
      "v  现在；正好；仅仅；几乎；很；表示强烈赞同；表示无法解释或不喜欢但不能改变的事；稍等一会儿；幸亏，幸好；突如其来地；出乎意料地；真倒楣；不如；做；",
      "adj  公正的，公平的；正义的；罪有应得；",
      "adv  现在；正好；仅仅；几乎；很；表示强烈赞同；表示无法解释或不喜欢但不能改变的事；稍等一会儿；幸亏，幸好；突如其来地；出乎意料地；真倒楣；不如；做；"
    ]
  },
  {
    "word": "justice",
    "explanations": [
      "n  公正；法律；法官；公平地对待；合理地处理；充分发挥自己的能力；"
    ]
  },
  {
    "word": "Justice",
    "explanations": [
      "n  基层法院法官；地方治安法官；",
      "other  基层法院法官；地方治安法官；"
    ]
  },
  {
    "word": "justifiable",
    "explanations": [
      "adj  无可非议的，有充分理由的；"
    ]
  },
  {
    "word": "justifiable",
    "explanations": [
      "n  尤指正当防卫时的；"
    ]
  },
  {
    "word": "justification",
    "explanations": [
      "n  正当的理由；辩解；"
    ]
  },
  {
    "word": "justified",
    "explanations": [
      "adj  有正当理由的；"
    ]
  },
  {
    "word": "justify",
    "explanations": [
      "v  为；我真的找不出理由再多休一天假了；"
    ]
  },
  {
    "word": "just-in-time",
    "explanations": [
      "adj  按需生产的，及时制度的；"
    ]
  },
  {
    "word": "jut",
    "explanations": [
      "v  使；"
    ]
  },
  {
    "word": "jute",
    "explanations": [
      "n  黄麻纤维；"
    ]
  },
  {
    "word": "juvenile",
    "explanations": [
      "n  少年；",
      "adj  青少年的；"
    ]
  },
  {
    "word": "juvenile",
    "explanations": [
      "n  少年犯；"
    ]
  },
  {
    "word": "juvenile",
    "explanations": [
      "n  主角；"
    ]
  },
  {
    "word": "juxtapose",
    "explanations": [
      "v  把；"
    ]
  }
]